across/__init__.py
across/sdk/__init__.py
across/sdk/v1/__init__.py
across/sdk/v1/abstract_credential_storage.py
across/sdk/v1/api_client.py
across/sdk/v1/api_client_wrapper.py
across/sdk/v1/api_response.py
across/sdk/v1/configuration.py
across/sdk/v1/exceptions.py
across/sdk/v1/py.typed
across/sdk/v1/rest.py
across/sdk/v1/api/__init__.py
across/sdk/v1/api/auth_api.py
across/sdk/v1/api/filter_api.py
across/sdk/v1/api/group_api.py
across/sdk/v1/api/group_invite_api.py
across/sdk/v1/api/group_role_api.py
across/sdk/v1/api/instrument_api.py
across/sdk/v1/api/internal_api.py
across/sdk/v1/api/observation_api.py
across/sdk/v1/api/observatory_api.py
across/sdk/v1/api/permission_api.py
across/sdk/v1/api/role_api.py
across/sdk/v1/api/schedule_api.py
across/sdk/v1/api/service_account_api.py
across/sdk/v1/api/telescope_api.py
across/sdk/v1/api/tle_api.py
across/sdk/v1/api/tools_api.py
across/sdk/v1/api/user_api.py
across/sdk/v1/models/__init__.py
across/sdk/v1/models/access_token_response.py
across/sdk/v1/models/across_server_routes_v1_group_invite_schemas_group_invite.py
across/sdk/v1/models/across_server_routes_v1_group_role_schemas_group_role.py
across/sdk/v1/models/across_server_routes_v1_group_role_schemas_service_account.py
across/sdk/v1/models/across_server_routes_v1_group_role_schemas_user.py
across/sdk/v1/models/across_server_routes_v1_group_schemas_group.py
across/sdk/v1/models/across_server_routes_v1_group_schemas_user.py
across/sdk/v1/models/across_server_routes_v1_role_schemas_user.py
across/sdk/v1/models/across_server_routes_v1_system_service_account_schemas_service_account.py
across/sdk/v1/models/across_server_routes_v1_system_service_account_schemas_service_account_secret.py
across/sdk/v1/models/across_server_routes_v1_user_schemas_group.py
across/sdk/v1/models/across_server_routes_v1_user_schemas_group_invite.py
across/sdk/v1/models/across_server_routes_v1_user_schemas_group_role.py
across/sdk/v1/models/across_server_routes_v1_user_schemas_user.py
across_server_openapi_python-1.1.1.dist-info/licenses/LICENSE
across_server_openapi_python-1.1.1.dist-info/METADATA
across_server_openapi_python-1.1.1.dist-info/WHEEL
across_server_openapi_python-1.1.1.dist-info/top_level.txt
across_server_openapi_python-1.1.1.dist-info/RECORD
