Metadata-Version: 2.4
Name: across-server-openapi-python
Version: 1.1.1
Summary: FastAPI
Home-page: 
Author: OpenAPI Generator community
Author-email: OpenAPI Generator Community <team@openapitools.org>
License:                                  Apache License
Project-URL: Repository, https://github.com/NASA-ACROSS/across-server-openapi-python
Keywords: OpenAPI,OpenAPI-Generator,FastAPI
Requires-Python: >3.9
License-File: LICENSE
Requires-Dist: urllib3<3.0.0,>=2.1.0
Requires-Dist: python-dateutil>=2.8.2
Requires-Dist: pydantic>=2
Requires-Dist: typing-extensions>=4.7.1
Dynamic: author
Dynamic: license-file
